setup.py
./__init__.py
./isolate.py
./populater.py
populater.egg-info/PKG-INFO
populater.egg-info/SOURCES.txt
populater.egg-info/dependency_links.txt
populater.egg-info/top_level.txt